<?xml version="1.0" encoding="UTF-8"?>
<s:scufl xmlns:s="http://org.embl.ebi.escience/xscufl/0.1alpha" version="0.2" log="0">
  <s:workflowdescription lsid="urn:lsid:net.sf.taverna:wfDefinition:e76467e0-81f5-4732-805f-bc9f3d7da30f" author="Alan R Williams" title="Concatenate two strings - empty strings">The concatenate two strings service takes two empty strings and returns an empty string.</s:workflowdescription>
  <s:processor name="Concatenate_two_strings">
    <s:defaults>
      <s:default name="string1" />
      <s:default name="string2" />
    </s:defaults>
    <s:local>org.embl.ebi.escience.scuflworkers.java.StringConcat</s:local>
  </s:processor>
  <s:link source="Concatenate_two_strings:output" sink="out" />
  <s:sink name="out" />
</s:scufl>

